suvtools/__init__.py
suvtools/calc_area.py
suvtools/fit_gauss.py
suvtools/fit_lorentz.py
suvtools/load.py
suvtools/lock_peak.py
suvtools/norm_bg.py
suvtools/save_csv.py
suvtools-1.2.0.dist-info/METADATA
suvtools-1.2.0.dist-info/WHEEL
suvtools-1.2.0.dist-info/licenses/LICENSE
suvtools-1.2.0.dist-info/RECORD
