Metadata-Version: 2.4
Name: suvtools
Version: 1.2.0
Summary: Python library for analyzing and visualizing SSLS SUV Beamline data.
License: MIT
License-File: LICENSE
Keywords: condensed-matter-physics,data-analysis,materials-science,matplotlib,python
Author: Pranab Das
Requires-Python: >=3.10,<4.0
Classifier: License :: OSI Approved :: MIT License
Classifier: Programming Language :: Python :: 3
Classifier: Programming Language :: Python :: 3.10
Classifier: Programming Language :: Python :: 3.11
Classifier: Programming Language :: Python :: 3.12
Classifier: Programming Language :: Python :: 3.13
Classifier: Programming Language :: Python :: 3.14
Provides-Extra: lint
Provides-Extra: notebook
Requires-Dist: autopep8 (>=2.3.2) ; extra == "lint"
Requires-Dist: jupyterlab (>=4.4.5) ; extra == "notebook"
Requires-Dist: matplotlib (>=3.10.5)
Requires-Dist: numpy (>=2.2.6)
Requires-Dist: pandas (>=2.3.1)
Requires-Dist: scipy (>=1.15.3)
Project-URL: Documentation, https://pranabdas.github.io/suvtools/docs/
Project-URL: Homepage, https://pranabdas.github.io/suvtools/
Project-URL: Repository, https://github.com/pranabdas/suvtools
